MANIFEST.in
README.md
setup.py
featurExtract/__init__.py
featurExtract/command_gb.py
featurExtract/command_gff.py
featurExtract/feature_extract.py
featurExtract/genBank_extract.py
featurExtract/parameter.py
featurExtract/version.py
featurExtract.egg-info/PKG-INFO
featurExtract.egg-info/SOURCES.txt
featurExtract.egg-info/dependency_links.txt
featurExtract.egg-info/entry_points.txt
featurExtract.egg-info/requires.txt
featurExtract.egg-info/top_level.txt
featurExtract/commands/__init__.py
featurExtract/commands/extract_cds.py
featurExtract/commands/extract_dorf.py
featurExtract/commands/extract_exon.py
featurExtract/commands/extract_gene.py
featurExtract/commands/extract_igr.py
featurExtract/commands/extract_intron.py
featurExtract/commands/extract_motif.py
featurExtract/commands/extract_mrna.py
featurExtract/commands/extract_promoter.py
featurExtract/commands/extract_rRNA.py
featurExtract/commands/extract_tRNA.py
featurExtract/commands/extract_terminator.py
featurExtract/commands/extract_transcript.py
featurExtract/commands/extract_uorf.py
featurExtract/commands/extract_utr.py
featurExtract/database/database.py
featurExtract/utils/__init__.py
featurExtract/utils/coverage.py
featurExtract/utils/util.py
featurExtract/utils/visualize.py