Metadata-Version: 2.1
Name: featurExtract
Version: 0.2.5.9
Summary: Extract genome ferature sequence for biologists
Home-page: https://github.com/SitaoZ/featurExtract.git
Author: zhusitao
Author-email: zhusitao1990@163.com
License: MIT
Keywords: genome feature,extract
Platform: UNKNOWN
Requires-Python: >=3.7.6
